hdl/gaussian_blur.sv
// Taken and partially modified from https://github.com/georgeyhere/FPGA-Video-Processing/blob/master/rtl/ps_gaussian.v

`timescale 1ns / 1ps
`default_nettype none

module gaussian #(parameter WIDTH = 8) (
                    input wire clk_in,
                    input wire rst_in,

                    input wire[WIDTH*3-1:0] r0_data_in,
                    input wire[WIDTH*3-1:0] r1_data_in,
                    input wire[WIDTH*3-1:0] r2_data_in,
                    input wire data_valid_in,

                    output logic[WIDTH-1:0] data_out,
                    output logic data_valid_out,

                    output logic error_out,
                    output logic busy_out);

    integer i;

    //  3x3 kernel
    logic [7:0] kernel [8:0];
    // KERNEL DEFINITION: 3X3 GAUSSIAN BLUR
    initial begin
        kernel[0] = 1;
        kernel[1] = 2;
        kernel[2] = 1;
        kernel[3] = 2;
        kernel[4] = 4;
        kernel[5] = 2;
        kernel[6] = 1;
        kernel[7] = 2;
        kernel[8] = 1;
    end

    // stage 1: multiply
    logic [WIDTH*9-1:0]     rowdata;
    logic [WIDTH+2:0]       stage1_data [8:0];
    logic                   stage1_valid;

    logic                   stage1_reg_valid;
    logic [WIDTH+2:0]       stage1_data_reg [8:0];
    

    // stage 2: accumulate
    logic [WIDTH+3:0]       stage2_accumulator;
    logic [WIDTH+3:0]       stage2_data;
    logic                   stage2_valid;

    // stage 3: divide by 16
    logic [WIDTH+3:0]       stage3_data;
    logic                   stage3_valid;

    // PIPELINE STAGE 1 (2 cycles)
    //
    assign rowdata = {r0_data_in, r1_data_in, r2_data_in};

    // multiply pixel data by kernel
    always_ff@(posedge clk_in) begin
        if(rst_in) begin
            stage1_valid <= 0;
            for(i=0; i<9; i=i+1) begin
                stage1_data[i] <= 0;
            end
        end
        else begin
            stage1_valid <= data_valid_in;
            for(i=0; i<9; i=i+1) begin
                stage1_data[i] <= $signed(kernel[i]) * 
                                  $signed({1'b0, rowdata[i*8+:8]});
            end
        end
    end

    // another register here for performance
    always_ff@(posedge clk_in) begin
        if(rst_in) begin
            stage1_reg_valid <= 0;
            for(i=0; i<9; i=i+1) begin
                stage1_data_reg[i] <= 0;
            end
        end
        else begin
            stage1_reg_valid <= stage1_valid;
            for(i=0; i<9; i=i+1) begin
                stage1_data_reg[i] <= stage1_data[i];
            end
        end
    end

    // PIPELINE STAGE 2 (1 cycle)
    //
    // sum all the stage 1 data
    always_comb begin
        stage2_accumulator = 0;
        for(i=0;  i<9; i=i+1) begin
            stage2_accumulator = $signed(stage2_accumulator) +
                                 $signed(stage1_data_reg[i]);
        end
    end

    // and register it
    always_ff@(posedge clk_in) begin
        if(rst_in) begin
            stage2_valid <= 0;
            stage2_data  <= 0;
        end
        else begin
            stage2_valid <= stage1_reg_valid;
            stage2_data  <= stage2_accumulator;
        end
    end

    // PIPELINE STAGE 3 (1 cycle)
    //
    // divide by 16 and output
    always_ff@(posedge clk_in) begin
        if(rst_in) begin
            data_valid_out <= 0;
            data_out  <= 0;
        end
        else begin
            data_valid_out <= stage2_valid;
            data_out  <= stage2_data >> 4; // stage2 is WIDTH+3 bits, output is WIDTH bits
        end
    end

endmodule

`default_nettype wire

sim/gaussian_blur_tb.sv
`timescale 1ns / 1ps
`default_nettype none

module gaussian_blur_tb;
    parameter WIDTH = 8;

    //make logics for inputs and outputs!
    logic clk_in;
    logic rst_in;
    logic [WIDTH*3-1:0] r0;
    logic [WIDTH*3-1:0] r1;
    logic [WIDTH*3-1:0] r2;
    logic valid_in;
    logic [WIDTH-1:0] data_out;
    logic valid_out;

    gaussian blur(.clk_in(clk_in), .rst_in(rst_in),
                         .r0_data_in(r0),
                         .r1_data_in(r1),
                         .r2_data_in(r2),
                         .data_valid_in(valid_in),
                         .data_out(data_out),
                         .data_valid_out(valid_out), 
                         .error_out(),
                         .busy_out());
    always begin
        #5;  //every 5 ns switch...so period of clock is 10 ns...100 MHz clock
        clk_in = !clk_in;
    end

    //initial block...this is our test simulation
    initial begin
        $dumpfile("blur.vcd"); //file to store value change dump (vcd)
        $dumpvars(0,gaussian_blur_tb); //store everything at the current level and below
        $display("Starting Sim"); //print nice message
        clk_in = 0; //initialize clk (super important)
        rst_in = 0; //initialize rst (super important)
        r0 = 24'h00_00_00;
        r1 = 24'h00_00_00;
        r2 = 24'h00_00_00;
        valid_in = 0;
        #10  //wait a little bit of time at beginning
        rst_in = 1; //reset system
        #10; //hold high for a few clock cycles
        rst_in=0;
        #10;

        // Test 1 
        $display("Test 1, all zeros");
        r0 = 24'h00_00_00;
        r1 = 24'h00_00_00;
        r2 = 24'h00_00_00;
        valid_in = 1;
        #10
        valid_in = 0;
        #100;
        $display("Test 1 done");
        $display("Blurred pixel Value:", data_out);

        // Test 2
        $display("Test 2, all ones");
        r0 = 24'h01_01_01;
        r1 = 24'h01_01_01;
        r2 = 24'h01_01_01;
        valid_in = 1;
        #10
        valid_in = 0;
        #100;
        $display("Test 2 done");
        $display("Blurred pixel Value:", data_out);

        // Test 3
        $display("Test 3, 1-9 square");
        r0 = 24'h01_02_03;
        r1 = 24'h04_05_06;
        r2 = 24'h07_08_09;
        valid_in = 1;
        #10
        valid_in = 0;
        #100;
        $display("Test 3 done");
        $display("Blurred pixel Value:", data_out);

        // Test 4
        $display("Test 4, all 255");
        r0 = 24'hFF_FF_FF;
        r1 = 24'hFF_FF_FF;
        r2 = 24'hFF_FF_FF;
        valid_in = 1;
        #10
        valid_in = 0;
        #100;
        $display("Test 4 done");
        $display("Blurred pixel Value:", data_out);

        // Test 5
        $display("Test 5, 255 middle");
        r0 = 24'h00_00_00;
        r1 = 24'h00_FF_00;
        r2 = 24'h00_00_00;
        valid_in = 1;
        #10
        valid_in = 0;
        #100;
        $display("Test 5 done");
        $display("Blurred pixel Value:", data_out);

        // Test 6
        $display("Test 6, random numbers");
        r0 = 24'h86_02_2E;
        r1 = 24'h1E_19_00;
        r2 = 24'h01_09_FF;
        valid_in = 1;
        #10
        valid_in = 0;
        #100;
        $display("Test 6 done");
        $display("Blurred pixel Value:", data_out);
        

        $display("Finishing Sim"); //print nice message
        $finish;
    end
endmodule //gaussian_blur_tb

`default_nettype wire

blur.vcd
$date
	Fri Nov 24 22:07:56 2023
$end
$version
	Icarus Verilog
$end
$timescale
	1ps
$end
$scope module gaussian_blur_tb $end
$var wire 1 ! valid_out $end
$var wire 8 " data_out [7:0] $end
$var parameter 32 # WIDTH $end
$var reg 1 $ clk_in $end
$var reg 24 % r0 [23:0] $end
$var reg 24 & r1 [23:0] $end
$var reg 24 ' r2 [23:0] $end
$var reg 1 ( rst_in $end
$var reg 1 ) valid_in $end
$scope module blur $end
$var wire 1 $ clk_in $end
$var wire 1 ) data_valid_in $end
$var wire 24 * r0_data_in [23:0] $end
$var wire 24 + r1_data_in [23:0] $end
$var wire 24 , r2_data_in [23:0] $end
$var wire 1 ( rst_in $end
$var wire 72 - rowdata [71:0] $end
$var parameter 32 . WIDTH $end
$var reg 1 / busy_out $end
$var reg 8 0 data_out [7:0] $end
$var reg 1 ! data_valid_out $end
$var reg 1 1 error_out $end
$var reg 1 2 stage1_reg_valid $end
$var reg 1 3 stage1_valid $end
$var reg 12 4 stage2_accumulator [11:0] $end
$var reg 12 5 stage2_data [11:0] $end
$var reg 1 6 stage2_valid $end
$var integer 32 7 i [31:0] $end
$upscope $end
$upscope $end
$enddefinitions $end
$comment Show the parameter values. $end
$dumpall
b1000 .
b1000 #
$end
#0
$dumpvars
b1001 7
x6
bx 5
bx 4
x3
x2
x1
bx 0
x/
b0 -
b0 ,
b0 +
b0 *
0)
0(
b0 '
b0 &
b0 %
0$
bx "
x!
$end
#5000
03
b1001 7
1$
#10000
0$
1(
#15000
b0 4
b0 "
b0 0
0!
b0 5
06
02
b1001 7
1$
#20000
0$
0(
#25000
b1001 7
1$
#30000
0$
1)
#35000
13
b1001 7
1$
#40000
0$
0)
#45000
03
12
b1001 7
1$
#50000
0$
#55000
16
02
b1001 7
1$
#60000
0$
#65000
06
1!
b1001 7
1$
#70000
0$
#75000
0!
b1001 7
1$
#80000
0$
#85000
b1001 7
1$
#90000
0$
#95000
b1001 7
1$
#100000
0$
#105000
b1001 7
1$
#110000
0$
#115000
b1001 7
1$
#120000
0$
#125000
b1001 7
1$
#130000
0$
#135000
b1001 7
1$
#140000
0$
1)
b10000000100000001 '
b10000000100000001 ,
b10000000100000001 &
b10000000100000001 +
b10000000100000001000000010000000100000001000000010000000100000001 -
b10000000100000001 %
b10000000100000001 *
#145000
13
b1001 7
1$
#150000
0$
0)
#155000
b10000 4
12
03
b1001 7
1$
#160000
0$
#165000
02
b10000 5
16
b1001 7
1$
#170000
0$
#175000
b1 "
b1 0
1!
06
b1001 7
1$
#180000
0$
#185000
0!
b1001 7
1$
#190000
0$
#195000
b1001 7
1$
#200000
0$
#205000
b1001 7
1$
#210000
0$
#215000
b1001 7
1$
#220000
0$
#225000
b1001 7
1$
#230000
0$
#235000
b1001 7
1$
#240000
0$
#245000
b1001 7
1$
#250000
0$
1)
b1110000100000001001 '
b1110000100000001001 ,
b1000000010100000110 &
b1000000010100000110 +
b10000001000000011000001000000010100000110000001110000100000001001 -
b10000001000000011 %
b10000001000000011 *
#255000
13
b1001 7
1$
#260000
0$
0)
#265000
b1010000 4
03
12
b1001 7
1$
#270000
0$
#275000
b1010000 5
16
02
b1001 7
1$
#280000
0$
#285000
06
b101 "
b101 0
1!
b1001 7
1$
#290000
0$
#295000
0!
b1001 7
1$
#300000
0$
#305000
b1001 7
1$
#310000
0$
#315000
b1001 7
1$
#320000
0$
#325000
b1001 7
1$
#330000
0$
#335000
b1001 7
1$
#340000
0$
#345000
b1001 7
1$
#350000
0$
#355000
b1001 7
1$
#360000
0$
1)
b111111111111111111111111 '
b111111111111111111111111 ,
b111111111111111111111111 &
b111111111111111111111111 +
b111111111111111111111111111111111111111111111111111111111111111111111111 -
b111111111111111111111111 %
b111111111111111111111111 *
#365000
13
b1001 7
1$
#370000
0$
0)
#375000
b111111110000 4
12
03
b1001 7
1$
#380000
0$
#385000
02
b111111110000 5
16
b1001 7
1$
#390000
0$
#395000
b11111111 "
b11111111 0
1!
06
b1001 7
1$
#400000
0$
#405000
0!
b1001 7
1$
#410000
0$
#415000
b1001 7
1$
#420000
0$
#425000
b1001 7
1$
#430000
0$
#435000
b1001 7
1$
#440000
0$
#445000
b1001 7
1$
#450000
0$
#455000
b1001 7
1$
#460000
0$
#465000
b1001 7
1$
#470000
0$
1)
b0 '
b0 ,
b1111111100000000 &
b1111111100000000 +
b1111111100000000000000000000000000000000 -
b0 %
b0 *
#475000
13
b1001 7
1$
#480000
0$
0)
#485000
b1111111100 4
03
12
b1001 7
1$
#490000
0$
#495000
b1111111100 5
16
02
b1001 7
1$
#500000
0$
#505000
06
b111111 "
b111111 0
1!
b1001 7
1$
#510000
0$
#515000
0!
b1001 7
1$
#520000
0$
#525000
b1001 7
1$
#530000
0$
#535000
b1001 7
1$
#540000
0$
#545000
b1001 7
1$
#550000
0$
#555000
b1001 7
1$
#560000
0$
#565000
b1001 7
1$
#570000
0$
#575000
b1001 7
1$
#580000
0$
1)
b10000100111111111 '
b10000100111111111 ,
b111100001100100000000 &
b111100001100100000000 +
b100001100000001000101110000111100001100100000000000000010000100111111111 -
b100001100000001000101110 %
b100001100000001000101110 *
#585000
13
b1001 7
1$
#590000
0$
0)
#595000
b1001101010 4
12
03
b1001 7
1$
#600000
0$
#605000
02
b1001101010 5
16
b1001 7
1$
#610000
0$
#615000
b100110 "
b100110 0
1!
06
b1001 7
1$
#620000
0$
#625000
0!
b1001 7
1$
#630000
0$
#635000
b1001 7
1$
#640000
0$
#645000
b1001 7
1$
#650000
0$
#655000
b1001 7
1$
#660000
0$
#665000
b1001 7
1$
#670000
0$
#675000
b1001 7
1$
#680000
0$
#685000
b1001 7
1$
