hdl/image_resize.sv
`timescale 1ns / 1ps
`default_nettype none

module image_half #( 
                    parameter BIT_DEPTH = 8,
                    parameter NEW_HEIGHT = 32
                    ) (
                    input wire clk_in,
                    input wire rst_in,

                    input wire[BIT_DEPTH-1:0] data_in,
                    input wire[7:0] data_x_in,
                    input wire[7:0] data_y_in,
                    input wire data_valid_in,

                    output logic[BIT_DEPTH-1:0] data_out,
                    output logic[7:0] data_addr_out,
                    output logic data_valid_out,

                    output logic error_out,
                    output logic busy_out);

    always_ff @(posedge clk_in) begin
        if (rst_in) begin
            data_out <= 0;
            data_addr_out <= 0;
            data_valid_out <= 0;
        end else begin
            if (data_valid_in) begin
                if (data_x_in[0] == 0 && data_y_in[0] == 0) begin
                    data_out <= data_in;
                    data_addr_out <= (data_y_in >> 1) * NEW_HEIGHT + (data_x_in >> 1);
                    data_valid_out <= 1;
                end
                else begin
                    data_valid_out <= 0;
                end
            end
            else begin
                data_valid_out <= 0;
            end
        end
    end

endmodule

`default_nettype wire

sim/image_resize_tb.sv
`timescale 1ns / 1ps
`default_nettype none

module img_resize_tb;

    //make logics for inputs and outputs!
    logic clk_in;
    logic rst_in;
    logic [7:0] pixel_in;
    logic [7:0] center_addr_x;
    logic [7:0] center_addr_y;
    logic valid_in;
    logic [7:0] data_out;
    logic [7:0] addr_out;
    logic valid_out;

    image_half #(.BIT_DEPTH(8),
                 .NEW_HEIGHT(32))
        downsizer(
            .clk_in(clk_in),
            .rst_in(rst_in),
            .data_in(pixel_in),
            .data_x_in(center_addr_x),
            .data_y_in(center_addr_y),
            .data_valid_in(valid_in),
            .data_out(data_out),
            .data_addr_out(addr_out),
            .data_valid_out(valid_out),
            .error_out(),
            .busy_out()
    );
    always begin
        #5;  //every 5 ns switch...so period of clock is 10 ns...100 MHz clock
        clk_in = !clk_in;
    end

    //initial block...this is our test simulation
    initial begin
        $dumpfile("resize.vcd"); //file to store value change dump (vcd)
        $dumpvars(0,img_resize_tb); //store everything at the current level and below
        $display("Starting Sim"); //print nice message
        clk_in = 0; //initialize clk (super important)
        rst_in = 0; //initialize rst (super important)
        center_addr_x = 0;
        center_addr_y = 0;
        valid_in = 0;
        #10  //wait a little bit of time at beginning
        rst_in = 1; //reset system
        #10; //hold high for a few clock cycles
        rst_in=0;
        #10;
        
        for (int i = 0; i<64; i= i+1)begin
            for (int j=0; j<64; j=j+1) begin
                pixel_in = i + j;
                valid_in = 1;
                #10
                valid_in = 0;
                #10
                center_addr_x = center_addr_x + 1;
            end
            center_addr_y = center_addr_y + 1;
            center_addr_x = 0;
        end
        

        $display("Finishing Sim"); //print nice message
        $finish;
    end
endmodule //gaussian_blur_tb

`default_nettype wire

resize.vcd
$date
	Sun Nov 26 02:18:54 2023
$end
$version
	Icarus Verilog
$end
$timescale
	1ps
$end
$scope module img_resize_tb $end
$var wire 1 ! valid_out $end
$var wire 8 " data_out [7:0] $end
$var wire 8 # addr_out [7:0] $end
$var reg 8 $ center_addr_x [7:0] $end
$var reg 8 % center_addr_y [7:0] $end
$var reg 1 & clk_in $end
$var reg 8 ' pixel_in [7:0] $end
$var reg 1 ( rst_in $end
$var reg 1 ) valid_in $end
$scope module downsizer $end
$var wire 1 & clk_in $end
$var wire 8 * data_in [7:0] $end
$var wire 1 ) data_valid_in $end
$var wire 8 + data_x_in [7:0] $end
$var wire 8 , data_y_in [7:0] $end
$var wire 1 ( rst_in $end
$var parameter 32 - BIT_DEPTH $end
$var parameter 32 . NEW_HEIGHT $end
$var reg 1 / busy_out $end
$var reg 8 0 data_addr_out [7:0] $end
$var reg 8 1 data_out [7:0] $end
$var reg 1 ! data_valid_out $end
$var reg 1 2 error_out $end
$upscope $end
$scope begin $ivl_for_loop0 $end
$var integer 32 3 i [31:0] $end
$scope begin $ivl_for_loop1 $end
$var integer 32 4 j [31:0] $end
$upscope $end
$upscope $end
$upscope $end
$enddefinitions $end
$comment Show the parameter values. $end
$dumpall
b100000 .
b1000 -
$end
#0
$dumpvars
b0 4
b0 3
x2
bx 1
bx 0
x/
b0 ,
b0 +
bx *
0)
0(
bx '
0&
b0 %
b0 $
bx #
bx "
x!
$end
#5000
0!
1&
#10000
0&
1(
#15000
b0 #
b0 0
b0 "
b0 1
1&
#20000
0&
0(
#25000
1&
#30000
0&
1)
b0 '
b0 *
#35000
1!
1&
#40000
0&
0)
#45000
0!
1&
#50000
0&
1)
b1 '
b1 *
b1 4
b1 $
b1 +
#55000
1&
#60000
0&
0)
#65000
1&
#70000
0&
1)
b10 '
b10 *
b10 4
b10 $
b10 +
#75000
1!
b1 #
b1 0
b10 "
b10 1
1&
#80000
0&
0)
#85000
0!
1&
#90000
0&
1)
b11 '
b11 *
b11 4
b11 $
b11 +
#95000
1&
#100000
0&
0)
#105000
1&
#110000
0&
1)
b100 '
b100 *
b100 4
b100 $
b100 +
#115000
1!
b10 #
b10 0
b100 "
b100 1
1&
#120000
0&
0)
#125000
0!
1&
#130000
0&
1)
b101 '
b101 *
b101 4
b101 $
b101 +
#135000
1&
#140000
0&
0)
#145000
1&
#150000
0&
1)
b110 '
b110 *
b110 4
b110 $
b110 +
#155000
1!
b11 #
b11 0
b110 "
b110 1
1&
#160000
0&
0)
#165000
0!
1&
#170000
0&
1)
b111 '
b111 *
b111 4
b111 $
b111 +
#175000
1&
#180000
0&
0)
#185000
1&
#190000
0&
1)
b1000 '
b1000 *
b1000 4
b1000 $
b1000 +
#195000
1!
b100 #
b100 0
b1000 "
b1000 1
1&
#200000
0&
0)
#205000
0!
1&
#210000
0&
1)
b1001 '
b1001 *
b1001 4
b1001 $
b1001 +
#215000
1&
#220000
0&
0)
#225000
1&
#230000
0&
1)
b1010 '
b1010 *
b1010 4
b1010 $
b1010 +
#235000
1!
b101 #
b101 0
b1010 "
b1010 1
1&
#240000
0&
0)
#245000
0!
1&
#250000
0&
1)
b1011 '
b1011 *
b1011 4
b1011 $
b1011 +
#255000
1&
#260000
0&
0)
#265000
1&
#270000
0&
1)
b1100 '
b1100 *
b1100 4
b1100 $
b1100 +
#275000
1!
b110 #
b110 0
b1100 "
b1100 1
1&
#280000
0&
0)
#285000
0!
1&
#290000
0&
1)
b1101 '
b1101 *
b1101 4
b1101 $
b1101 +
#295000
1&
#300000
0&
0)
#305000
1&
#310000
0&
1)
b1110 '
b1110 *
b1110 4
b1110 $
b1110 +
#315000
1!
b111 #
b111 0
b1110 "
b1110 1
1&
#320000
0&
0)
#325000
0!
1&
#330000
0&
1)
b1111 '
b1111 *
b1111 4
b1111 $
b1111 +
#335000
1&
#340000
0&
0)
#345000
1&
#350000
0&
1)
b10000 '
b10000 *
b10000 4
b10000 $
b10000 +
#355000
1!
b1000 #
b1000 0
b10000 "
b10000 1
1&
#360000
0&
0)
#365000
0!
1&
#370000
0&
1)
b10001 '
b10001 *
b10001 4
b10001 $
b10001 +
#375000
1&
#380000
0&
0)
#385000
1&
#390000
0&
1)
b10010 '
b10010 *
b10010 4
b10010 $
b10010 +
#395000
1!
b1001 #
b1001 0
b10010 "
b10010 1
1&
#400000
0&
0)
#405000
0!
1&
#410000
0&
1)
b10011 '
b10011 *
b10011 4
b10011 $
b10011 +
#415000
1&
#420000
0&
0)
#425000
1&
#430000
0&
1)
b10100 '
b10100 *
b10100 4
b10100 $
b10100 +
#435000
1!
b1010 #
b1010 0
b10100 "
b10100 1
1&
#440000
0&
0)
#445000
0!
1&
#450000
0&
1)
b10101 '
b10101 *
b10101 4
b10101 $
b10101 +
#455000
1&
#460000
0&
0)
#465000
1&
#470000
0&
1)
b10110 '
b10110 *
b10110 4
b10110 $
b10110 +
#475000
1!
b1011 #
b1011 0
b10110 "
b10110 1
1&
#480000
0&
0)
#485000
0!
1&
#490000
0&
1)
b10111 '
b10111 *
b10111 4
b10111 $
b10111 +
#495000
1&
#500000
0&
0)
#505000
1&
#510000
0&
1)
b11000 '
b11000 *
b11000 4
b11000 $
b11000 +
#515000
1!
b1100 #
b1100 0
b11000 "
b11000 1
1&
#520000
0&
0)
#525000
0!
1&
#530000
0&
1)
b11001 '
b11001 *
b11001 4
b11001 $
b11001 +
#535000
1&
#540000
0&
0)
#545000
1&
#550000
0&
1)
b11010 '
b11010 *
b11010 4
b11010 $
b11010 +
#555000
1!
b1101 #
b1101 0
b11010 "
b11010 1
1&
#560000
0&
0)
#565000
0!
1&
#570000
0&
1)
b11011 '
b11011 *
b11011 4
b11011 $
b11011 +
#575000
1&
#580000
0&
0)
#585000
1&
#590000
0&
1)
b11100 '
b11100 *
b11100 4
b11100 $
b11100 +
#595000
1!
b1110 #
b1110 0
b11100 "
b11100 1
1&
#600000
0&
0)
#605000
0!
1&
#610000
0&
1)
b11101 '
b11101 *
b11101 4
b11101 $
b11101 +
#615000
1&
#620000
0&
0)
#625000
1&
#630000
0&
1)
b11110 '
b11110 *
b11110 4
b11110 $
b11110 +
#635000
1!
b1111 #
b1111 0
b11110 "
b11110 1
1&
#640000
0&
0)
#645000
0!
1&
#650000
0&
1)
b11111 '
b11111 *
b11111 4
b11111 $
b11111 +
#655000
1&
#660000
0&
0)
#665000
1&
#670000
0&
1)
b100000 '
b100000 *
b100000 4
b100000 $
b100000 +
#675000
1!
b10000 #
b10000 0
b100000 "
b100000 1
1&
#680000
0&
0)
#685000
0!
1&
#690000
0&
1)
b100001 '
b100001 *
b100001 4
b100001 $
b100001 +
#695000
1&
#700000
0&
0)
#705000
1&
#710000
0&
1)
b100010 '
b100010 *
b100010 4
b100010 $
b100010 +
#715000
1!
b10001 #
b10001 0
b100010 "
b100010 1
1&
#720000
0&
0)
#725000
0!
1&
#730000
0&
1)
b100011 '
b100011 *
b100011 4
b100011 $
b100011 +
#735000
1&
#740000
0&
0)
#745000
1&
#750000
0&
1)
b100100 '
b100100 *
b100100 4
b100100 $
b100100 +
#755000
1!
b10010 #
b10010 0
b100100 "
b100100 1
1&
#760000
0&
0)
#765000
0!
1&
#770000
0&
1)
b100101 '
b100101 *
b100101 4
b100101 $
b100101 +
#775000
1&
#780000
0&
0)
#785000
1&
#790000
0&
1)
b100110 '
b100110 *
b100110 4
b100110 $
b100110 +
#795000
1!
b10011 #
b10011 0
b100110 "
b100110 1
1&
#800000
0&
0)
#805000
0!
1&
#810000
0&
1)
b100111 '
b100111 *
b100111 4
b100111 $
b100111 +
#815000
1&
#820000
0&
0)
#825000
1&
#830000
0&
1)
b101000 '
b101000 *
b101000 4
b101000 $
b101000 +
#835000
1!
b10100 #
b10100 0
b101000 "
b101000 1
1&
#840000
0&
0)
#845000
0!
1&
#850000
0&
1)
b101001 '
b101001 *
b101001 4
b101001 $
b101001 +
#855000
1&
#860000
0&
0)
#865000
1&
#870000
0&
1)
b101010 '
b101010 *
b101010 4
b101010 $
b101010 +
#875000
1!
b10101 #
b10101 0
b101010 "
b101010 1
1&
#880000
0&
0)
#885000
0!
1&
#890000
0&
1)
b101011 '
b101011 *
b101011 4
b101011 $
b101011 +
#895000
1&
#900000
0&
0)
#905000
1&
#910000
0&
1)
b101100 '
b101100 *
b101100 4
b101100 $
b101100 +
#915000
1!
b10110 #
b10110 0
b101100 "
b101100 1
1&
#920000
0&
0)
#925000
0!
1&
#930000
0&
1)
b101101 '
b101101 *
b101101 4
b101101 $
b101101 +
#935000
1&
#940000
0&
0)
#945000
1&
#950000
0&
1)
b101110 '
b101110 *
b101110 4
b101110 $
b101110 +
#955000
1!
b10111 #
b10111 0
b101110 "
b101110 1
1&
#960000
0&
0)
#965000
0!
1&
#970000
0&
1)
b101111 '
b101111 *
b101111 4
b101111 $
b101111 +
#975000
1&
#980000
0&
0)
#985000
1&
#990000
0&
1)
b110000 '
b110000 *
b110000 4
b110000 $
b110000 +
#995000
1!
b11000 #
b11000 0
b110000 "
b110000 1
1&
#1000000
0&
0)
#1005000
0!
1&
#1010000
0&
1)
b110001 '
b110001 *
b110001 4
b110001 $
b110001 +
#1015000
1&
#1020000
0&
0)
#1025000
1&
#1030000
0&
1)
b110010 '
b110010 *
b110010 4
b110010 $
b110010 +
#1035000
1!
b11001 #
b11001 0
b110010 "
b110010 1
1&
#1040000
0&
0)
#1045000
0!
1&
#1050000
0&
1)
b110011 '
b110011 *
b110011 4
b110011 $
b110011 +
#1055000
1&
#1060000
0&
0)
#1065000
1&
#1070000
0&
1)
b110100 '
b110100 *
b110100 4
b110100 $
b110100 +
#1075000
1!
b11010 #
b11010 0
b110100 "
b110100 1
1&
#1080000
0&
0)
#1085000
0!
1&
#1090000
0&
1)
b110101 '
b110101 *
b110101 4
b110101 $
b110101 +
#1095000
1&
#1100000
0&
0)
#1105000
1&
#1110000
0&
1)
b110110 '
b110110 *
b110110 4
b110110 $
b110110 +
#1115000
1!
b11011 #
b11011 0
b110110 "
b110110 1
1&
#1120000
0&
0)
#1125000
0!
1&
#1130000
0&
1)
b110111 '
b110111 *
b110111 4
b110111 $
b110111 +
#1135000
1&
#1140000
0&
0)
#1145000
1&
#1150000
0&
1)
b111000 '
b111000 *
b111000 4
b111000 $
b111000 +
#1155000
1!
b11100 #
b11100 0
b111000 "
b111000 1
1&
#1160000
0&
0)
#1165000
0!
1&
#1170000
0&
1)
b111001 '
b111001 *
b111001 4
b111001 $
b111001 +
#1175000
1&
#1180000
0&
0)
#1185000
1&
#1190000
0&
1)
b111010 '
b111010 *
b111010 4
b111010 $
b111010 +
#1195000
1!
b11101 #
b11101 0
b111010 "
b111010 1
1&
#1200000
0&
0)
#1205000
0!
1&
#1210000
0&
1)
b111011 '
b111011 *
b111011 4
b111011 $
b111011 +
#1215000
1&
#1220000
0&
0)
#1225000
1&
#1230000
0&
1)
b111100 '
b111100 *
b111100 4
b111100 $
b111100 +
#1235000
1!
b11110 #
b11110 0
b111100 "
b111100 1
1&
#1240000
0&
0)
#1245000
0!
1&
#1250000
0&
1)
b111101 '
b111101 *
b111101 4
b111101 $
b111101 +
#1255000
1&
#1260000
0&
0)
#1265000
1&
#1270000
0&
1)
b111110 '
b111110 *
b111110 4
b111110 $
b111110 +
#1275000
1!
b11111 #
b11111 0
b111110 "
b111110 1
1&
#1280000
0&
0)
#1285000
0!
1&
#1290000
0&
1)
b111111 '
b111111 *
b111111 4
b111111 $
b111111 +
#1295000
1&
#1300000
0&
0)
#1305000
1&
#1310000
0&
1)
b1 '
b1 *
b1 3
b1 %
b1 ,
b0 4
b0 $
b0 +
#1315000
1&
#1320000
0&
0)
#1325000
1&
#1330000
0&
1)
b10 '
b10 *
b1 4
b1 $
b1 +
#1335000
1&
#1340000
0&
0)
#1345000
1&
#1350000
0&
1)
b11 '
b11 *
b10 4
b10 $
b10 +
#1355000
1&
#1360000
0&
0)
#1365000
1&
#1370000
0&
1)
b100 '
b100 *
b11 4
b11 $
b11 +
#1375000
1&
#1380000
0&
0)
#1385000
1&
#1390000
0&
1)
b101 '
b101 *
b100 4
b100 $
b100 +
#1395000
1&
#1400000
0&
0)
#1405000
1&
#1410000
0&
1)
b110 '
b110 *
b101 4
b101 $
b101 +
#1415000
1&
#1420000
0&
0)
#1425000
1&
#1430000
0&
1)
b111 '
b111 *
b110 4
b110 $
b110 +
#1435000
1&
#1440000
0&
0)
#1445000
1&
#1450000
0&
1)
b1000 '
b1000 *
b111 4
b111 $
b111 +
#1455000
1&
#1460000
0&
0)
#1465000
1&
#1470000
0&
1)
b1001 '
b1001 *
b1000 4
b1000 $
b1000 +
#1475000
1&
#1480000
0&
0)
#1485000
1&
#1490000
0&
1)
b1010 '
b1010 *
b1001 4
b1001 $
b1001 +
#1495000
1&
#1500000
0&
0)
#1505000
1&
#1510000
0&
1)
b1011 '
b1011 *
b1010 4
b1010 $
b1010 +
#1515000
1&
#1520000
0&
0)
#1525000
1&
#1530000
0&
1)
b1100 '
b1100 *
b1011 4
b1011 $
b1011 +
#1535000
1&
#1540000
0&
0)
#1545000
1&
#1550000
0&
1)
b1101 '
b1101 *
b1100 4
b1100 $
b1100 +
#1555000
1&
#1560000
0&
0)
#1565000
1&
#1570000
0&
1)
b1110 '
b1110 *
b1101 4
b1101 $
b1101 +
#1575000
1&
#1580000
0&
0)
#1585000
1&
#1590000
0&
1)
b1111 '
b1111 *
b1110 4
b1110 $
b1110 +
#1595000
1&
#1600000
0&
0)
#1605000
1&
#1610000
0&
1)
b10000 '
b10000 *
b1111 4
b1111 $
b1111 +
#1615000
1&
#1620000
0&
0)
#1625000
1&
#1630000
0&
1)
b10001 '
b10001 *
b10000 4
b10000 $
b10000 +
#1635000
1&
#1640000
0&
0)
#1645000
1&
#1650000
0&
1)
b10010 '
b10010 *
b10001 4
b10001 $
b10001 +
#1655000
1&
#1660000
0&
0)
#1665000
1&
#1670000
0&
1)
b10011 '
b10011 *
b10010 4
b10010 $
b10010 +
#1675000
1&
#1680000
0&
0)
#1685000
1&
#1690000
0&
1)
b10100 '
b10100 *
b10011 4
b10011 $
b10011 +
#1695000
1&
#1700000
0&
0)
#1705000
1&
#1710000
0&
1)
b10101 '
b10101 *
b10100 4
b10100 $
b10100 +
#1715000
1&
#1720000
0&
0)
#1725000
1&
#1730000
0&
1)
b10110 '
b10110 *
b10101 4
b10101 $
b10101 +
#1735000
1&
#1740000
0&
0)
#1745000
1&
#1750000
0&
1)
b10111 '
b10111 *
b10110 4
b10110 $
b10110 +
#1755000
1&
#1760000
0&
0)
#1765000
1&
#1770000
0&
1)
b11000 '
b11000 *
b10111 4
b10111 $
b10111 +
#1775000
1&
#1780000
0&
0)
#1785000
1&
#1790000
0&
1)
b11001 '
b11001 *
b11000 4
b11000 $
b11000 +
#1795000
1&
#1800000
0&
0)
#1805000
1&
#1810000
0&
1)
b11010 '
b11010 *
b11001 4
b11001 $
b11001 +
#1815000
1&
#1820000
0&
0)
#1825000
1&
#1830000
0&
1)
b11011 '
b11011 *
b11010 4
b11010 $
b11010 +
#1835000
1&
#1840000
0&
0)
#1845000
1&
#1850000
0&
1)
b11100 '
b11100 *
b11011 4
b11011 $
b11011 +
#1855000
1&
#1860000
0&
0)
#1865000
1&
#1870000
0&
1)
b11101 '
b11101 *
b11100 4
b11100 $
b11100 +
#1875000
1&
#1880000
0&
0)
#1885000
1&
#1890000
0&
1)
b11110 '
b11110 *
b11101 4
b11101 $
b11101 +
#1895000
1&
#1900000
0&
0)
#1905000
1&
#1910000
0&
1)
b11111 '
b11111 *
b11110 4
b11110 $
b11110 +
#1915000
1&
#1920000
0&
0)
#1925000
1&
#1930000
0&
1)
b100000 '
b100000 *
b11111 4
b11111 $
b11111 +
#1935000
1&
#1940000
0&
0)
#1945000
1&
#1950000
0&
1)
b100001 '
b100001 *
b100000 4
b100000 $
b100000 +
#1955000
1&
#1960000
0&
0)
#1965000
1&
#1970000
0&
1)
b100010 '
b100010 *
b100001 4
b100001 $
b100001 +
#1975000
1&
#1980000
0&
0)
#1985000
1&
#1990000
0&
1)
b100011 '
b100011 *
b100010 4
b100010 $
b100010 +
#1995000
1&
#2000000
0&
0)
#2005000
1&
#2010000
0&
1)
b100100 '
b100100 *
b100011 4
b100011 $
b100011 +
#2015000
1&
#2020000
0&
0)
#2025000
1&
#2030000
0&
1)
b100101 '
b100101 *
b100100 4
b100100 $
b100100 +
#2035000
1&
#2040000
0&
0)
#2045000
1&
#2050000
0&
1)
b100110 '
b100110 *
b100101 4
b100101 $
b100101 +
#2055000
1&
#2060000
0&
0)
#2065000
1&
#2070000
0&
1)
b100111 '
b100111 *
b100110 4
b100110 $
b100110 +
#2075000
1&
#2080000
0&
0)
#2085000
1&
#2090000
0&
1)
b101000 '
b101000 *
b100111 4
b100111 $
b100111 +
#2095000
1&
#2100000
0&
0)
#2105000
1&
#2110000
0&
1)
b101001 '
b101001 *
b101000 4
b101000 $
b101000 +
#2115000
1&
#2120000
0&
0)
#2125000
1&
#2130000
0&
1)
b101010 '
b101010 *
b101001 4
b101001 $
b101001 +
#2135000
1&
#2140000
0&
0)
#2145000
1&
#2150000
0&
1)
b101011 '
b101011 *
b101010 4
b101010 $
b101010 +
#2155000
1&
#2160000
0&
0)
#2165000
1&
#2170000
0&
1)
b101100 '
b101100 *
b101011 4
b101011 $
b101011 +
#2175000
1&
#2180000
0&
0)
#2185000
1&
#2190000
0&
1)
b101101 '
b101101 *
b101100 4
b101100 $
b101100 +
#2195000
1&
#2200000
0&
0)
#2205000
1&
#2210000
0&
1)
b101110 '
b101110 *
b101101 4
b101101 $
b101101 +
#2215000
1&
#2220000
0&
0)
#2225000
1&
#2230000
0&
1)
b101111 '
b101111 *
b101110 4
b101110 $
b101110 +
#2235000
1&
#2240000
0&
0)
#2245000
1&
#2250000
0&
1)
b110000 '
b110000 *
b101111 4
b101111 $
b101111 +
#2255000
1&
#2260000
0&
0)
#2265000
1&
#2270000
0&
1)
b110001 '
b110001 *
b110000 4
b110000 $
b110000 +
#2275000
1&
#2280000
0&
0)
#2285000
1&
#2290000
0&
1)
b110010 '
b110010 *
b110001 4
b110001 $
b110001 +
#2295000
1&
#2300000
0&
0)
#2305000
1&
#2310000
0&
1)
b110011 '
b110011 *
b110010 4
b110010 $
b110010 +
#2315000
1&
#2320000
0&
0)
#2325000
1&
#2330000
0&
1)
b110100 '
b110100 *
b110011 4
b110011 $
b110011 +
#2335000
1&
#2340000
0&
0)
#2345000
1&
#2350000
0&
1)
b110101 '
b110101 *
b110100 4
b110100 $
b110100 +
#2355000
1&
#2360000
0&
0)
#2365000
1&
#2370000
0&
1)
b110110 '
b110110 *
b110101 4
b110101 $
b110101 +
#2375000
1&
#2380000
0&
0)
#2385000
1&
#2390000
0&
1)
b110111 '
b110111 *
b110110 4
b110110 $
b110110 +
#2395000
1&
#2400000
0&
0)
#2405000
1&
#2410000
0&
1)
b111000 '
b111000 *
b110111 4
b110111 $
b110111 +
#2415000
1&
#2420000
0&
0)
#2425000
1&
#2430000
0&
1)
b111001 '
b111001 *
b111000 4
b111000 $
b111000 +
#2435000
1&
#2440000
0&
0)
#2445000
1&
#2450000
0&
1)
b111010 '
b111010 *
b111001 4
b111001 $
b111001 +
#2455000
1&
#2460000
0&
0)
#2465000
1&
#2470000
0&
1)
b111011 '
b111011 *
b111010 4
b111010 $
b111010 +
#2475000
1&
#2480000
0&
0)
#2485000
1&
#2490000
0&
1)
b111100 '
b111100 *
b111011 4
b111011 $
b111011 +
#2495000
1&
#2500000
0&
0)
#2505000
1&
#2510000
0&
1)
b111101 '
b111101 *
b111100 4
b111100 $
b111100 +
#2515000
1&
#2520000
0&
0)
#2525000
1&
#2530000
0&
1)
b111110 '
b111110 *
b111101 4
b111101 $
b111101 +
#2535000
1&
#2540000
0&
0)
#2545000
1&
#2550000
0&
1)
b111111 '
b111111 *
b111110 4
b111110 $
b111110 +
#2555000
1&
#2560000
0&
0)
#2565000
1&
#2570000
0&
1)
b1000000 '
b1000000 *
b111111 4
b111111 $
b111111 +
#2575000
1&
#2580000
0&
0)
#2585000
1&
#2590000
0&
1)
b10 '
b10 *
b10 3
b10 %
b10 ,
b0 4
b0 $
b0 +
#2595000
1!
b100000 #
b100000 0
b10 "
b10 1
1&
#2600000
0&
0)
#2605000
0!
1&
#2610000
0&
1)
b11 '
b11 *
b1 4
b1 $
b1 +
#2615000
1&
#2620000
0&
0)
#2625000
1&
#2630000
0&
1)
b100 '
b100 *
b10 4
b10 $
b10 +
#2635000
1!
b100001 #
b100001 0
b100 "
b100 1
1&
#2640000
0&
0)
#2645000
0!
1&
#2650000
0&
1)
b101 '
b101 *
b11 4
b11 $
b11 +
#2655000
1&
#2660000
0&
0)
#2665000
1&
#2670000
0&
1)
b110 '
b110 *
b100 4
b100 $
b100 +
#2675000
1!
b100010 #
b100010 0
b110 "
b110 1
1&
#2680000
0&
0)
#2685000
0!
1&
#2690000
0&
1)
b111 '
b111 *
b101 4
b101 $
b101 +
#2695000
1&
#2700000
0&
0)
#2705000
1&
#2710000
0&
1)
b1000 '
b1000 *
b110 4
b110 $
b110 +
#2715000
1!
b100011 #
b100011 0
b1000 "
b1000 1
1&
#2720000
0&
0)
#2725000
0!
1&
#2730000
0&
1)
b1001 '
b1001 *
b111 4
b111 $
b111 +
#2735000
1&
#2740000
0&
0)
#2745000
1&
#2750000
0&
1)
b1010 '
b1010 *
b1000 4
b1000 $
b1000 +
#2755000
1!
b100100 #
b100100 0
b1010 "
b1010 1
1&
#2760000
0&
0)
#2765000
0!
1&
#2770000
0&
1)
b1011 '
b1011 *
b1001 4
b1001 $
b1001 +
#2775000
1&
#2780000
0&
0)
#2785000
1&
#2790000
0&
1)
b1100 '
b1100 *
b1010 4
b1010 $
b1010 +
#2795000
1!
b100101 #
b100101 0
b1100 "
b1100 1
1&
#2800000
0&
0)
#2805000
0!
1&
#2810000
0&
1)
b1101 '
b1101 *
b1011 4
b1011 $
b1011 +
#2815000
1&
#2820000
0&
0)
#2825000
1&
#2830000
0&
1)
b1110 '
b1110 *
b1100 4
b1100 $
b1100 +
#2835000
1!
b100110 #
b100110 0
b1110 "
b1110 1
1&
#2840000
0&
0)
#2845000
0!
1&
#2850000
0&
1)
b1111 '
b1111 *
b1101 4
b1101 $
b1101 +
#2855000
1&
#2860000
0&
0)
#2865000
1&
#2870000
0&
1)
b10000 '
b10000 *
b1110 4
b1110 $
b1110 +
#2875000
1!
b100111 #
b100111 0
b10000 "
b10000 1
1&
#2880000
0&
0)
#2885000
0!
1&
#2890000
0&
1)
b10001 '
b10001 *
b1111 4
b1111 $
b1111 +
#2895000
1&
#2900000
0&
0)
#2905000
1&
#2910000
0&
1)
b10010 '
b10010 *
b10000 4
b10000 $
b10000 +
#2915000
1!
b101000 #
b101000 0
b10010 "
b10010 1
1&
#2920000
0&
0)
#2925000
0!
1&
#2930000
0&
1)
b10011 '
b10011 *
b10001 4
b10001 $
b10001 +
#2935000
1&
#2940000
0&
0)
#2945000
1&
#2950000
0&
1)
b10100 '
b10100 *
b10010 4
b10010 $
b10010 +
#2955000
1!
b101001 #
b101001 0
b10100 "
b10100 1
1&
#2960000
0&
0)
#2965000
0!
1&
#2970000
0&
1)
b10101 '
b10101 *
b10011 4
b10011 $
b10011 +
#2975000
1&
#2980000
0&
0)
#2985000
1&
#2990000
0&
1)
b10110 '
b10110 *
b10100 4
b10100 $
b10100 +
#2995000
1!
b101010 #
b101010 0
b10110 "
b10110 1
1&
#3000000
0&
0)
#3005000
0!
1&
#3010000
0&
1)
b10111 '
b10111 *
b10101 4
b10101 $
b10101 +
#3015000
1&
#3020000
0&
0)
#3025000
1&
#3030000
0&
1)
b11000 '
b11000 *
b10110 4
b10110 $
b10110 +
#3035000
1!
b101011 #
b101011 0
b11000 "
b11000 1
1&
#3040000
0&
0)
#3045000
0!
1&
#3050000
0&
1)
b11001 '
b11001 *
b10111 4
b10111 $
b10111 +
#3055000
1&
#3060000
0&
0)
#3065000
1&
#3070000
0&
1)
b11010 '
b11010 *
b11000 4
b11000 $
b11000 +
#3075000
1!
b101100 #
b101100 0
b11010 "
b11010 1
1&
#3080000
0&
0)
#3085000
0!
1&
#3090000
0&
1)
b11011 '
b11011 *
b11001 4
b11001 $
b11001 +
#3095000
1&
#3100000
0&
0)
#3105000
1&
#3110000
0&
1)
b11100 '
b11100 *
b11010 4
b11010 $
b11010 +
#3115000
1!
b101101 #
b101101 0
b11100 "
b11100 1
1&
#3120000
0&
0)
#3125000
0!
1&
#3130000
0&
1)
b11101 '
b11101 *
b11011 4
b11011 $
b11011 +
#3135000
1&
#3140000
0&
0)
#3145000
1&
#3150000
0&
1)
b11110 '
b11110 *
b11100 4
b11100 $
b11100 +
#3155000
1!
b101110 #
b101110 0
b11110 "
b11110 1
1&
#3160000
0&
0)
#3165000
0!
1&
#3170000
0&
1)
b11111 '
b11111 *
b11101 4
b11101 $
b11101 +
#3175000
1&
#3180000
0&
0)
#3185000
1&
#3190000
0&
1)
b100000 '
b100000 *
b11110 4
b11110 $
b11110 +
#3195000
1!
b101111 #
b101111 0
b100000 "
b100000 1
1&
#3200000
0&
0)
#3205000
0!
1&
#3210000
0&
1)
b100001 '
b100001 *
b11111 4
b11111 $
b11111 +
#3215000
1&
#3220000
0&
0)
#3225000
1&
#3230000
0&
1)
b100010 '
b100010 *
b100000 4
b100000 $
b100000 +
#3235000
1!
b110000 #
b110000 0
b100010 "
b100010 1
1&
#3240000
0&
0)
#3245000
0!
1&
#3250000
0&
1)
b100011 '
b100011 *
b100001 4
b100001 $
b100001 +
#3255000
1&
#3260000
0&
0)
#3265000
1&
#3270000
0&
1)
b100100 '
b100100 *
b100010 4
b100010 $
b100010 +
#3275000
1!
b110001 #
b110001 0
b100100 "
b100100 1
1&
#3280000
0&
0)
#3285000
0!
1&
#3290000
0&
1)
b100101 '
b100101 *
b100011 4
b100011 $
b100011 +
#3295000
1&
#3300000
0&
0)
#3305000
1&
#3310000
0&
1)
b100110 '
b100110 *
b100100 4
b100100 $
b100100 +
#3315000
1!
b110010 #
b110010 0
b100110 "
b100110 1
1&
#3320000
0&
0)
#3325000
0!
1&
#3330000
0&
1)
b100111 '
b100111 *
b100101 4
b100101 $
b100101 +
#3335000
1&
#3340000
0&
0)
#3345000
1&
#3350000
0&
1)
b101000 '
b101000 *
b100110 4
b100110 $
b100110 +
#3355000
1!
b110011 #
b110011 0
b101000 "
b101000 1
1&
#3360000
0&
0)
#3365000
0!
1&
#3370000
0&
1)
b101001 '
b101001 *
b100111 4
b100111 $
b100111 +
#3375000
1&
#3380000
0&
0)
#3385000
1&
#3390000
0&
1)
b101010 '
b101010 *
b101000 4
b101000 $
b101000 +
#3395000
1!
b110100 #
b110100 0
b101010 "
b101010 1
1&
#3400000
0&
0)
#3405000
0!
1&
#3410000
0&
1)
b101011 '
b101011 *
b101001 4
b101001 $
b101001 +
#3415000
1&
#3420000
0&
0)
#3425000
1&
